.DS_Store
ascii_image_art/__init__.py
ascii_image_art/ascii_images_and_text.py
ascii_image_art/constants.py
ascii_image_art/main.py
ascii_image_art/usingAI.py
ascii_image_art-0.0.5.4.dist-info/LICENCE
ascii_image_art-0.0.5.4.dist-info/METADATA
ascii_image_art-0.0.5.4.dist-info/WHEEL
ascii_image_art-0.0.5.4.dist-info/top_level.txt
ascii_image_art-0.0.5.4.dist-info/RECORD
