Metadata-Version: 2.1
Name: ascii-image-art
Version: 0.0.5.4
Summary: A simple to use Python library to convert images into ASCII characters text file and ASCII characters colored images. Option to use new AI module.
Home-page: https://github.com/txtasad/Ascii-Image-Art
Author: Mohammad Asad
License: MIT
Keywords: python,ascii,image to text,image to ascii,color ascii image,text image,ASAD,MOHAMMAD ASAD,ascii_art,ascii-image
Classifier: Operating System :: OS Independent
Classifier: License :: OSI Approved :: BSD License
Classifier: Programming Language :: Python :: 3.0
Classifier: Development Status :: 5 - Production/Stable
Classifier: Intended Audience :: Developers
Classifier: Intended Audience :: Education
Classifier: Intended Audience :: Financial and Insurance Industry
Classifier: Intended Audience :: Science/Research
Classifier: Natural Language :: English
License-File: LICENCE
